slice/__init__.py
slice/__main__.py
slice/slicing.py
slice/tests/__init__.py
slice/tests/test_slice.py
slice_shukuru-1.0.2.dist-info/LICENSE
slice_shukuru-1.0.2.dist-info/METADATA
slice_shukuru-1.0.2.dist-info/WHEEL
slice_shukuru-1.0.2.dist-info/top_level.txt
slice_shukuru-1.0.2.dist-info/RECORD
