Metadata-Version: 2.1
Name: slice-shukuru
Version: 1.0.2
Summary: Simple file splitter
Home-page: https://gitlab.com/p6323/slice
Author: Florent 'Shukuru' DUPONT
Author-email: fdgd@flodup.dev
License: UNKNOWN
Project-URL: Bug Tracker, https://gitlab.com/p6323/slice/-/issues
Platform: UNKNOWN
Classifier: Programming Language :: Python :: 3
Classifier: License :: OSI Approved :: BSD License
Classifier: Operating System :: OS Independent
Requires-Python: >=3.9
License-File: LICENSE
Requires-Dist: humanfriendly (==10.0)
